{"uuid":"d0a5f46b-d3e1-4d33-aa2e-e6b6b64c8867","uuid_short":"d0a5f46bd3e14d33aa2ee6b6b64c8867","data":{"1496013902129":{"stats":{"stat.mineBlock.minecraft.spruce_fence":1,"stat.flyOneCm":36462,"stat.deaths":1,"stat.walkOneCm":4766,"stat.jump":175,"stat.playOneMinute":6255,"stat.fallOneCm":9032,"achievement.openInventory":1,"stat.leaveGame":1,"stat.sneakTime":15,"stat.damageTaken":230,"stat.pickup.minecraft.spruce_fence":1,"stat.timeSinceDeath":42,"stat.useItem.minecraft.spruce_fence":1,"stat.sprintOneCm":17384,"achievement.exploreAllBiomes":{"value":0,"progress":["Ice Plains","Ice Mountains"]}},"data":{"_seen":1495938203605,"time_start":1495937889225,"time_last":1495938203605,"time_lived":312.65,"uuid":"d0a5f46b-d3e1-4d33-aa2e-e6b6b64c8867","uuid_short":"d0a5f46bd3e14d33aa2ee6b6b64c8867","playername":"lofivo","names":[{"name":"lofivo","changedToAt":1495895426000},{"name":"mc_lofivo"}],"banned":false}},"1496100339850":{"stats":{"stat.mineBlock.minecraft.spruce_fence":1,"stat.flyOneCm":36462,"stat.deaths":1,"stat.walkOneCm":4766,"stat.jump":175,"stat.playOneMinute":6255,"stat.fallOneCm":9032,"achievement.openInventory":1,"stat.leaveGame":1,"stat.sneakTime":15,"stat.damageTaken":230,"stat.pickup.minecraft.spruce_fence":1,"stat.timeSinceDeath":42,"stat.useItem.minecraft.spruce_fence":1,"stat.sprintOneCm":17384,"achievement.exploreAllBiomes":{"value":0,"progress":["Ice Plains","Ice Mountains"]}},"data":{"_seen":1495938203605,"time_start":1495937889225,"time_last":1495938203605,"time_lived":312.65,"uuid":"d0a5f46b-d3e1-4d33-aa2e-e6b6b64c8867","uuid_short":"d0a5f46bd3e14d33aa2ee6b6b64c8867","playername":"lofivo","names":[{"name":"lofivo","changedToAt":1495895426000},{"name":"mc_lofivo"}],"banned":false}},"1496186890730":{"stats":{"stat.mineBlock.minecraft.spruce_fence":1,"stat.flyOneCm":36462,"stat.deaths":1,"stat.walkOneCm":4766,"stat.jump":175,"stat.playOneMinute":6255,"stat.fallOneCm":9032,"achievement.openInventory":1,"stat.leaveGame":1,"stat.sneakTime":15,"stat.damageTaken":230,"stat.pickup.minecraft.spruce_fence":1,"stat.timeSinceDeath":42,"stat.useItem.minecraft.spruce_fence":1,"stat.sprintOneCm":17384,"achievement.exploreAllBiomes":{"value":0,"progress":["Ice Plains","Ice Mountains"]}},"data":{"_seen":1495938203605,"time_start":1495937889225,"time_last":1495938203605,"time_lived":312.65,"uuid":"d0a5f46b-d3e1-4d33-aa2e-e6b6b64c8867","uuid_short":"d0a5f46bd3e14d33aa2ee6b6b64c8867","playername":"lofivo","names":[{"name":"lofivo","changedToAt":1495895426000},{"name":"mc_lofivo"}],"banned":false}},"1496273210938":{"stats":{"stat.mineBlock.minecraft.spruce_fence":1,"stat.flyOneCm":36462,"stat.deaths":1,"stat.walkOneCm":4766,"stat.jump":175,"stat.playOneMinute":6255,"stat.fallOneCm":9032,"achievement.openInventory":1,"stat.leaveGame":1,"stat.sneakTime":15,"stat.damageTaken":230,"stat.pickup.minecraft.spruce_fence":1,"stat.timeSinceDeath":42,"stat.useItem.minecraft.spruce_fence":1,"stat.sprintOneCm":17384,"achievement.exploreAllBiomes":{"value":0,"progress":["Ice Plains","Ice Mountains"]}},"data":{"_seen":1495938203605,"time_start":1495937889225,"time_last":1495938203605,"time_lived":312.65,"uuid":"d0a5f46b-d3e1-4d33-aa2e-e6b6b64c8867","uuid_short":"d0a5f46bd3e14d33aa2ee6b6b64c8867","playername":"lofivo","names":[{"name":"lofivo","changedToAt":1495895426000},{"name":"mc_lofivo"}],"banned":false}},"1496359606857":{"stats":{"stat.mineBlock.minecraft.spruce_fence":1,"stat.flyOneCm":36462,"stat.deaths":1,"stat.walkOneCm":4766,"stat.jump":175,"stat.playOneMinute":6255,"stat.fallOneCm":9032,"achievement.openInventory":1,"stat.leaveGame":1,"stat.sneakTime":15,"stat.damageTaken":230,"stat.pickup.minecraft.spruce_fence":1,"stat.timeSinceDeath":42,"stat.useItem.minecraft.spruce_fence":1,"stat.sprintOneCm":17384,"achievement.exploreAllBiomes":{"value":0,"progress":["Ice Plains","Ice Mountains"]}},"data":{"_seen":1495938203605,"time_start":1495937889225,"time_last":1495938203605,"time_lived":312.65,"uuid":"d0a5f46b-d3e1-4d33-aa2e-e6b6b64c8867","uuid_short":"d0a5f46bd3e14d33aa2ee6b6b64c8867","playername":"lofivo","names":[{"name":"lofivo","changedToAt":1495895426000},{"name":"mc_lofivo"}],"banned":false}},"1496445980287":{"stats":{"stat.mineBlock.minecraft.spruce_fence":1,"stat.flyOneCm":36462,"stat.deaths":1,"stat.walkOneCm":4766,"stat.jump":175,"stat.playOneMinute":6255,"stat.fallOneCm":9032,"achievement.openInventory":1,"stat.leaveGame":1,"stat.sneakTime":15,"stat.damageTaken":230,"stat.pickup.minecraft.spruce_fence":1,"stat.timeSinceDeath":42,"stat.useItem.minecraft.spruce_fence":1,"stat.sprintOneCm":17384,"achievement.exploreAllBiomes":{"value":0,"progress":["Ice Plains","Ice Mountains"]}},"data":{"_seen":1495938203605,"time_start":1495937889225,"time_last":1495938203605,"time_lived":312.65,"uuid":"d0a5f46b-d3e1-4d33-aa2e-e6b6b64c8867","uuid_short":"d0a5f46bd3e14d33aa2ee6b6b64c8867","playername":"lofivo","names":[{"name":"lofivo","changedToAt":1495895426000},{"name":"mc_lofivo"}],"banned":false}},"1496532416645":{"stats":{"stat.mineBlock.minecraft.spruce_fence":1,"stat.flyOneCm":36462,"stat.deaths":1,"stat.walkOneCm":4766,"stat.jump":175,"stat.playOneMinute":6255,"stat.fallOneCm":9032,"achievement.openInventory":1,"stat.leaveGame":1,"stat.sneakTime":15,"stat.damageTaken":230,"stat.pickup.minecraft.spruce_fence":1,"stat.timeSinceDeath":42,"stat.useItem.minecraft.spruce_fence":1,"stat.sprintOneCm":17384,"achievement.exploreAllBiomes":{"value":0,"progress":["Ice Plains","Ice Mountains"]}},"data":{"_seen":1495938203605,"time_start":1495937889225,"time_last":1495938203605,"time_lived":312.65,"uuid":"d0a5f46b-d3e1-4d33-aa2e-e6b6b64c8867","uuid_short":"d0a5f46bd3e14d33aa2ee6b6b64c8867","playername":"lofivo","names":[{"name":"lofivo","changedToAt":1495895426000},{"name":"mc_lofivo"}],"banned":false}},"1496618848609":{"stats":{"stat.mineBlock.minecraft.spruce_fence":1,"stat.flyOneCm":36462,"stat.deaths":1,"stat.walkOneCm":4766,"stat.jump":175,"stat.playOneMinute":6255,"stat.fallOneCm":9032,"achievement.openInventory":1,"stat.leaveGame":1,"stat.sneakTime":15,"stat.damageTaken":230,"stat.pickup.minecraft.spruce_fence":1,"stat.timeSinceDeath":42,"stat.useItem.minecraft.spruce_fence":1,"stat.sprintOneCm":17384,"achievement.exploreAllBiomes":{"value":0,"progress":["Ice Plains","Ice Mountains"]}},"data":{"_seen":1495938203605,"time_start":1495937889225,"time_last":1495938203605,"time_lived":312.65,"uuid":"d0a5f46b-d3e1-4d33-aa2e-e6b6b64c8867","uuid_short":"d0a5f46bd3e14d33aa2ee6b6b64c8867","playername":"lofivo","names":[{"name":"lofivo","changedToAt":1495895426000},{"name":"mc_lofivo"}],"banned":false}},"1496705269919":{"stats":{"stat.mineBlock.minecraft.spruce_fence":1,"stat.flyOneCm":36462,"stat.deaths":1,"stat.walkOneCm":4766,"stat.jump":175,"stat.playOneMinute":6255,"stat.fallOneCm":9032,"achievement.openInventory":1,"stat.leaveGame":1,"stat.sneakTime":15,"stat.damageTaken":230,"stat.pickup.minecraft.spruce_fence":1,"stat.timeSinceDeath":42,"stat.useItem.minecraft.spruce_fence":1,"stat.sprintOneCm":17384,"achievement.exploreAllBiomes":{"value":0,"progress":["Ice Plains","Ice Mountains"]}},"data":{"_seen":1495938203605,"time_start":1495937889225,"time_last":1495938203605,"time_lived":312.65,"uuid":"d0a5f46b-d3e1-4d33-aa2e-e6b6b64c8867","uuid_short":"d0a5f46bd3e14d33aa2ee6b6b64c8867","playername":"lofivo","names":[{"name":"lofivo","changedToAt":1495895426000},{"name":"mc_lofivo"}],"banned":false}},"1496791708106":{"stats":{"stat.mineBlock.minecraft.spruce_fence":1,"stat.flyOneCm":36462,"stat.deaths":1,"stat.walkOneCm":4766,"stat.jump":175,"stat.playOneMinute":6255,"stat.fallOneCm":9032,"achievement.openInventory":1,"stat.leaveGame":1,"stat.sneakTime":15,"stat.damageTaken":230,"stat.pickup.minecraft.spruce_fence":1,"stat.timeSinceDeath":42,"stat.useItem.minecraft.spruce_fence":1,"stat.sprintOneCm":17384,"achievement.exploreAllBiomes":{"value":0,"progress":["Ice Plains","Ice Mountains"]}},"data":{"_seen":1495938203605,"time_start":1495937889225,"time_last":1495938203605,"time_lived":312.65,"uuid":"d0a5f46b-d3e1-4d33-aa2e-e6b6b64c8867","uuid_short":"d0a5f46bd3e14d33aa2ee6b6b64c8867","playername":"lofivo","names":[{"name":"lofivo","changedToAt":1495895426000},{"name":"mc_lofivo"}],"banned":false}},"1496878164732":{"stats":{"stat.mineBlock.minecraft.spruce_fence":1,"stat.flyOneCm":36462,"stat.deaths":1,"stat.walkOneCm":4766,"stat.jump":175,"stat.playOneMinute":6255,"stat.fallOneCm":9032,"achievement.openInventory":1,"stat.leaveGame":1,"stat.sneakTime":15,"stat.damageTaken":230,"stat.pickup.minecraft.spruce_fence":1,"stat.timeSinceDeath":42,"stat.useItem.minecraft.spruce_fence":1,"stat.sprintOneCm":17384,"achievement.exploreAllBiomes":{"value":0,"progress":["Ice Plains","Ice Mountains"]}},"data":{"_seen":1495938203605,"time_start":1495937889225,"time_last":1495938203605,"time_lived":312.65,"uuid":"d0a5f46b-d3e1-4d33-aa2e-e6b6b64c8867","uuid_short":"d0a5f46bd3e14d33aa2ee6b6b64c8867","playername":"lofivo","names":[{"name":"lofivo","changedToAt":1495895426000},{"name":"mc_lofivo"}],"banned":false}},"1496964573056":{"stats":{"stat.mineBlock.minecraft.spruce_fence":1,"stat.flyOneCm":36462,"stat.deaths":1,"stat.walkOneCm":4766,"stat.jump":175,"stat.playOneMinute":6255,"stat.fallOneCm":9032,"achievement.openInventory":1,"stat.leaveGame":1,"stat.sneakTime":15,"stat.damageTaken":230,"stat.pickup.minecraft.spruce_fence":1,"stat.timeSinceDeath":42,"stat.useItem.minecraft.spruce_fence":1,"stat.sprintOneCm":17384,"achievement.exploreAllBiomes":{"value":0,"progress":["Ice Plains","Ice Mountains"]}},"data":{"_seen":1495938203605,"time_start":1495937889225,"time_last":1495938203605,"time_lived":312.65,"uuid":"d0a5f46b-d3e1-4d33-aa2e-e6b6b64c8867","uuid_short":"d0a5f46bd3e14d33aa2ee6b6b64c8867","playername":"lofivo","names":[{"name":"lofivo","changedToAt":1495895426000},{"name":"mc_lofivo"}],"banned":false}},"1497050857208":{"stats":{"stat.mineBlock.minecraft.spruce_fence":1,"stat.flyOneCm":36462,"stat.deaths":1,"stat.walkOneCm":4766,"stat.jump":175,"stat.playOneMinute":6255,"stat.fallOneCm":9032,"achievement.openInventory":1,"stat.leaveGame":1,"stat.sneakTime":15,"stat.damageTaken":230,"stat.pickup.minecraft.spruce_fence":1,"stat.timeSinceDeath":42,"stat.useItem.minecraft.spruce_fence":1,"stat.sprintOneCm":17384,"achievement.exploreAllBiomes":{"value":0,"progress":["Ice Plains","Ice Mountains"]}},"data":{"_seen":1495938203605,"time_start":1495937889225,"time_last":1495938203605,"time_lived":312.65,"uuid":"d0a5f46b-d3e1-4d33-aa2e-e6b6b64c8867","uuid_short":"d0a5f46bd3e14d33aa2ee6b6b64c8867","playername":"lofivo","names":[{"name":"lofivo","changedToAt":1495895426000},{"name":"mc_lofivo"}],"banned":false}},"1497137269688":{"stats":{"stat.mineBlock.minecraft.spruce_fence":1,"stat.flyOneCm":36462,"stat.deaths":1,"stat.walkOneCm":4766,"stat.jump":175,"stat.playOneMinute":6255,"stat.fallOneCm":9032,"achievement.openInventory":1,"stat.leaveGame":1,"stat.sneakTime":15,"stat.damageTaken":230,"stat.pickup.minecraft.spruce_fence":1,"stat.timeSinceDeath":42,"stat.useItem.minecraft.spruce_fence":1,"stat.sprintOneCm":17384,"achievement.exploreAllBiomes":{"value":0,"progress":["Ice Plains","Ice Mountains"]}},"data":{"_seen":1495938203605,"time_start":1495937889225,"time_last":1495938203605,"time_lived":312.65,"uuid":"d0a5f46b-d3e1-4d33-aa2e-e6b6b64c8867","uuid_short":"d0a5f46bd3e14d33aa2ee6b6b64c8867","playername":"lofivo","names":[{"name":"lofivo","changedToAt":1495895426000},{"name":"mc_lofivo"}],"banned":false}},"1497764303415":{"advancements":{},"stats":{"stat.mineBlock.minecraft.spruce_fence":1,"stat.flyOneCm":36462,"stat.deaths":1,"stat.walkOneCm":4766,"stat.jump":175,"stat.playOneMinute":6255,"stat.fallOneCm":9032,"achievement.openInventory":1,"stat.leaveGame":1,"stat.sneakTime":15,"stat.damageTaken":230,"stat.pickup.minecraft.spruce_fence":1,"stat.timeSinceDeath":42,"stat.useItem.minecraft.spruce_fence":1,"stat.sprintOneCm":17384,"achievement.exploreAllBiomes":{"value":0,"progress":["Ice Plains","Ice Mountains"]}},"data":{"_seen":1495938203605,"time_start":1495937889225,"time_last":1495938203605,"time_lived":312.65,"uuid":"d0a5f46b-d3e1-4d33-aa2e-e6b6b64c8867","uuid_short":"d0a5f46bd3e14d33aa2ee6b6b64c8867","playername":"lofivo","names":[{"name":"lofivo","changedToAt":1495895426000},{"name":"mc_lofivo"}],"banned":false}},"1497805321681":{"advancements":{},"stats":{"stat.mineBlock.minecraft.spruce_fence":1,"stat.flyOneCm":36462,"stat.deaths":1,"stat.walkOneCm":4766,"stat.jump":175,"stat.playOneMinute":6255,"stat.fallOneCm":9032,"achievement.openInventory":1,"stat.leaveGame":1,"stat.sneakTime":15,"stat.damageTaken":230,"stat.pickup.minecraft.spruce_fence":1,"stat.timeSinceDeath":42,"stat.useItem.minecraft.spruce_fence":1,"stat.sprintOneCm":17384,"achievement.exploreAllBiomes":{"value":0,"progress":["Ice Plains","Ice Mountains"]}},"data":{"_seen":1495938203605,"time_start":1495937889225,"time_last":1495938203605,"time_lived":312.65,"uuid":"d0a5f46b-d3e1-4d33-aa2e-e6b6b64c8867","uuid_short":"d0a5f46bd3e14d33aa2ee6b6b64c8867","playername":"lofivo","names":[{"name":"lofivo","changedToAt":1495895426000},{"name":"mc_lofivo"}],"banned":false}},"1497979681947":{"advancements":{},"stats":{"stat.mineBlock.minecraft.spruce_fence":1,"stat.flyOneCm":36462,"stat.deaths":1,"stat.walkOneCm":4766,"stat.jump":175,"stat.playOneMinute":6255,"stat.fallOneCm":9032,"achievement.openInventory":1,"stat.leaveGame":1,"stat.sneakTime":15,"stat.damageTaken":230,"stat.pickup.minecraft.spruce_fence":1,"stat.timeSinceDeath":42,"stat.useItem.minecraft.spruce_fence":1,"stat.sprintOneCm":17384,"achievement.exploreAllBiomes":{"value":0,"progress":["Ice Plains","Ice Mountains"]}},"data":{"_seen":1495938203605,"time_start":1495937889225,"time_last":1495938203605,"time_lived":312.65,"uuid":"d0a5f46b-d3e1-4d33-aa2e-e6b6b64c8867","uuid_short":"d0a5f46bd3e14d33aa2ee6b6b64c8867","playername":"lofivo","names":[{"name":"lofivo","changedToAt":1495895426000},{"name":"mc_lofivo"}],"banned":false}},"1498144162738":{"advancements":{},"stats":{"stat.mineBlock.minecraft.spruce_fence":1,"stat.flyOneCm":36462,"stat.deaths":1,"stat.walkOneCm":4766,"stat.jump":175,"stat.playOneMinute":6255,"stat.fallOneCm":9032,"achievement.openInventory":1,"stat.leaveGame":1,"stat.sneakTime":15,"stat.damageTaken":230,"stat.pickup.minecraft.spruce_fence":1,"stat.timeSinceDeath":42,"stat.useItem.minecraft.spruce_fence":1,"stat.sprintOneCm":17384,"achievement.exploreAllBiomes":{"value":0,"progress":["Ice Plains","Ice Mountains"]}},"data":{"_seen":1495938203605,"time_start":1495937889225,"time_last":1495938203605,"time_lived":312.65,"uuid":"d0a5f46b-d3e1-4d33-aa2e-e6b6b64c8867","uuid_short":"d0a5f46bd3e14d33aa2ee6b6b64c8867","playername":"lofivo","names":[{"name":"lofivo","changedToAt":1495895426000},{"name":"mc_lofivo"}],"banned":false}},"1498150891908":{"advancements":{},"stats":{"stat.mineBlock.minecraft.spruce_fence":1,"stat.flyOneCm":36462,"stat.deaths":1,"stat.walkOneCm":4766,"stat.jump":175,"stat.playOneMinute":6255,"stat.fallOneCm":9032,"achievement.openInventory":1,"stat.leaveGame":1,"stat.sneakTime":15,"stat.damageTaken":230,"stat.pickup.minecraft.spruce_fence":1,"stat.timeSinceDeath":42,"stat.useItem.minecraft.spruce_fence":1,"stat.sprintOneCm":17384,"achievement.exploreAllBiomes":{"value":0,"progress":["Ice Plains","Ice Mountains"]}},"data":{"_seen":1495938203605,"time_start":1495937889225,"time_last":1495938203605,"time_lived":312.65,"uuid":"d0a5f46b-d3e1-4d33-aa2e-e6b6b64c8867","uuid_short":"d0a5f46bd3e14d33aa2ee6b6b64c8867","playername":"lofivo","names":[{"name":"lofivo","changedToAt":1495895426000},{"name":"mc_lofivo"}],"banned":false}},"1498237256902":{"advancements":{},"stats":{"stat.mineBlock.minecraft.spruce_fence":1,"stat.flyOneCm":36462,"stat.deaths":1,"stat.walkOneCm":4766,"stat.jump":175,"stat.playOneMinute":6255,"stat.fallOneCm":9032,"achievement.openInventory":1,"stat.leaveGame":1,"stat.sneakTime":15,"stat.damageTaken":230,"stat.pickup.minecraft.spruce_fence":1,"stat.timeSinceDeath":42,"stat.useItem.minecraft.spruce_fence":1,"stat.sprintOneCm":17384,"achievement.exploreAllBiomes":{"value":0,"progress":["Ice Plains","Ice Mountains"]}},"data":{"_seen":1495938203605,"time_start":1495937889225,"time_last":1495938203605,"time_lived":312.65,"uuid":"d0a5f46b-d3e1-4d33-aa2e-e6b6b64c8867","uuid_short":"d0a5f46bd3e14d33aa2ee6b6b64c8867","playername":"lofivo","names":[{"name":"lofivo","changedToAt":1495895426000},{"name":"mc_lofivo"}],"banned":false}},"1498323663465":{"advancements":{},"stats":{"stat.mineBlock.minecraft.spruce_fence":1,"stat.flyOneCm":36462,"stat.deaths":1,"stat.walkOneCm":4766,"stat.jump":175,"stat.playOneMinute":6255,"stat.fallOneCm":9032,"achievement.openInventory":1,"stat.leaveGame":1,"stat.sneakTime":15,"stat.damageTaken":230,"stat.pickup.minecraft.spruce_fence":1,"stat.timeSinceDeath":42,"stat.useItem.minecraft.spruce_fence":1,"stat.sprintOneCm":17384,"achievement.exploreAllBiomes":{"value":0,"progress":["Ice Plains","Ice Mountains"]}},"data":{"_seen":1495938203605,"time_start":1495937889225,"time_last":1495938203605,"time_lived":312.65,"uuid":"d0a5f46b-d3e1-4d33-aa2e-e6b6b64c8867","uuid_short":"d0a5f46bd3e14d33aa2ee6b6b64c8867","playername":"lofivo","names":[{"name":"lofivo","changedToAt":1495895426000},{"name":"mc_lofivo"}],"banned":false}},"1498410112171":{"advancements":{},"stats":{"stat.mineBlock.minecraft.spruce_fence":1,"stat.flyOneCm":36462,"stat.deaths":1,"stat.walkOneCm":4766,"stat.jump":175,"stat.playOneMinute":6255,"stat.fallOneCm":9032,"achievement.openInventory":1,"stat.leaveGame":1,"stat.sneakTime":15,"stat.damageTaken":230,"stat.pickup.minecraft.spruce_fence":1,"stat.timeSinceDeath":42,"stat.useItem.minecraft.spruce_fence":1,"stat.sprintOneCm":17384,"achievement.exploreAllBiomes":{"value":0,"progress":["Ice Plains","Ice Mountains"]}},"data":{"_seen":1495938203605,"time_start":1495937889225,"time_last":1495938203605,"time_lived":312.65,"uuid":"d0a5f46b-d3e1-4d33-aa2e-e6b6b64c8867","uuid_short":"d0a5f46bd3e14d33aa2ee6b6b64c8867","playername":"lofivo","names":[{"name":"lofivo","changedToAt":1495895426000},{"name":"mc_lofivo"}],"banned":false}},"1498496556774":{"advancements":{},"stats":{"stat.mineBlock.minecraft.spruce_fence":1,"stat.flyOneCm":36462,"stat.deaths":1,"stat.walkOneCm":4766,"stat.jump":175,"stat.playOneMinute":6255,"stat.fallOneCm":9032,"achievement.openInventory":1,"stat.leaveGame":1,"stat.sneakTime":15,"stat.damageTaken":230,"stat.pickup.minecraft.spruce_fence":1,"stat.timeSinceDeath":42,"stat.useItem.minecraft.spruce_fence":1,"stat.sprintOneCm":17384,"achievement.exploreAllBiomes":{"value":0,"progress":["Ice Plains","Ice Mountains"]}},"data":{"_seen":1495938203605,"time_start":1495937889225,"time_last":1495938203605,"time_lived":312.65,"uuid":"d0a5f46b-d3e1-4d33-aa2e-e6b6b64c8867","uuid_short":"d0a5f46bd3e14d33aa2ee6b6b64c8867","playername":"lofivo","names":[{"name":"lofivo","changedToAt":1495895426000},{"name":"mc_lofivo"}],"banned":false}},"1498582965562":{"advancements":{},"stats":{"stat.mineBlock.minecraft.spruce_fence":1,"stat.flyOneCm":36462,"stat.deaths":1,"stat.walkOneCm":4766,"stat.jump":175,"stat.playOneMinute":6255,"stat.fallOneCm":9032,"achievement.openInventory":1,"stat.leaveGame":1,"stat.sneakTime":15,"stat.damageTaken":230,"stat.pickup.minecraft.spruce_fence":1,"stat.timeSinceDeath":42,"stat.useItem.minecraft.spruce_fence":1,"stat.sprintOneCm":17384,"achievement.exploreAllBiomes":{"value":0,"progress":["Ice Plains","Ice Mountains"]}},"data":{"_seen":1495938203605,"time_start":1495937889225,"time_last":1495938203605,"time_lived":312.65,"uuid":"d0a5f46b-d3e1-4d33-aa2e-e6b6b64c8867","uuid_short":"d0a5f46bd3e14d33aa2ee6b6b64c8867","playername":"lofivo","names":[{"name":"lofivo","changedToAt":1495895426000},{"name":"mc_lofivo"}],"banned":false}},"1498669367224":{"advancements":{},"stats":{"stat.mineBlock.minecraft.spruce_fence":1,"stat.flyOneCm":36462,"stat.deaths":1,"stat.walkOneCm":4766,"stat.jump":175,"stat.playOneMinute":6255,"stat.fallOneCm":9032,"achievement.openInventory":1,"stat.leaveGame":1,"stat.sneakTime":15,"stat.damageTaken":230,"stat.pickup.minecraft.spruce_fence":1,"stat.timeSinceDeath":42,"stat.useItem.minecraft.spruce_fence":1,"stat.sprintOneCm":17384,"achievement.exploreAllBiomes":{"value":0,"progress":["Ice Plains","Ice Mountains"]}},"data":{"_seen":1495938203605,"time_start":1495937889225,"time_last":1495938203605,"time_lived":312.65,"uuid":"d0a5f46b-d3e1-4d33-aa2e-e6b6b64c8867","uuid_short":"d0a5f46bd3e14d33aa2ee6b6b64c8867","playername":"lofivo","names":[{"name":"lofivo","changedToAt":1495895426000},{"name":"mc_lofivo"}],"banned":false}},"1498755775990":{"advancements":{},"stats":{"stat.mineBlock.minecraft.spruce_fence":1,"stat.flyOneCm":36462,"stat.deaths":1,"stat.walkOneCm":4766,"stat.jump":175,"stat.playOneMinute":6255,"stat.fallOneCm":9032,"achievement.openInventory":1,"stat.leaveGame":1,"stat.sneakTime":15,"stat.damageTaken":230,"stat.pickup.minecraft.spruce_fence":1,"stat.timeSinceDeath":42,"stat.useItem.minecraft.spruce_fence":1,"stat.sprintOneCm":17384,"achievement.exploreAllBiomes":{"value":0,"progress":["Ice Plains","Ice Mountains"]}},"data":{"_seen":1495938203605,"time_start":1495937889225,"time_last":1495938203605,"time_lived":312.65,"uuid":"d0a5f46b-d3e1-4d33-aa2e-e6b6b64c8867","uuid_short":"d0a5f46bd3e14d33aa2ee6b6b64c8867","playername":"lofivo","names":[{"name":"lofivo","changedToAt":1495895426000},{"name":"mc_lofivo"}],"banned":false}}}}
